ULTRA/__init__.py
ULTRA/lib/python3.11/site-packages/ULTRA.so
ULTRA/lib/python3.12/site-packages/ULTRA.so
ULTRA/lib/python3.9/site-packages/ULTRA.so
ultra_crdex-6.1.dist-info/licenses/LICENSE
ultra_crdex-6.1.dist-info/METADATA
ultra_crdex-6.1.dist-info/WHEEL
ultra_crdex-6.1.dist-info/top_level.txt
ultra_crdex-6.1.dist-info/RECORD
